source_google_directory/__init__.py
source_google_directory/api.py
source_google_directory/client.py
source_google_directory/run.py
source_google_directory/schemas/group_members.json
source_google_directory/schemas/groups.json
source_google_directory/schemas/users.json
source_google_directory/source.py
source_google_directory/spec.json
source_google_directory/utils.py
airbyte_source_google_directory-0.2.44.dist-info/METADATA
airbyte_source_google_directory-0.2.44.dist-info/WHEEL
airbyte_source_google_directory-0.2.44.dist-info/entry_points.txt
airbyte_source_google_directory-0.2.44.dist-info/RECORD
