Metadata-Version: 2.3
Name: airbyte-source-google-directory
Version: 0.2.44
Summary: Source implementation for Google Directory.
License: MIT
Author: Airbyte
Author-email: contact@airbyte.io
Requires-Python: >=3.9,<3.12
Classifier: License :: OSI Approved :: MIT License
Classifier: Programming Language :: Python :: 3
Classifier: Programming Language :: Python :: 3.9
Classifier: Programming Language :: Python :: 3.10
Classifier: Programming Language :: Python :: 3.11
Requires-Dist: airbyte-cdk (==0.80.0)
Requires-Dist: backoff (==1.10.0)
Requires-Dist: google-api-python-client (==1.12.8)
Requires-Dist: google-auth-httplib2 (==0.0.4)
Requires-Dist: google-auth-oauthlib (==0.4.2)
Project-URL: Documentation, https://docs.airbyte.com/integrations/sources/google-directory
Project-URL: Homepage, https://airbyte.com
Project-URL: Repository, https://github.com/airbytehq/airbyte
